editidle/__init__.py
editidle/main.py
editidle-0.1.1.dist-info/METADATA
editidle-0.1.1.dist-info/WHEEL
editidle-0.1.1.dist-info/entry_points.txt
editidle-0.1.1.dist-info/top_level.txt
editidle-0.1.1.dist-info/RECORD
